pymocd/__init__.py
pymocd/pymocd.cpython-312-darwin.so
pymocd-1.5.1.dist-info/METADATA
pymocd-1.5.1.dist-info/WHEEL
pymocd-1.5.1.dist-info/licenses/LICENSE
pymocd-1.5.1.dist-info/RECORD
