Metadata-Version: 2.4
Name: pymocd
Version: 1.5.1
Classifier: Programming Language :: Python
Classifier: Programming Language :: Python :: 3
Classifier: Programming Language :: Python :: 3 :: Only
Classifier: Programming Language :: Python :: 3.10
Classifier: Programming Language :: Python :: 3.11
Classifier: Programming Language :: Python :: 3.12
Classifier: Programming Language :: Python :: 3.13
Classifier: Programming Language :: Rust
Classifier: Intended Audience :: Developers
Classifier: Intended Audience :: Information Technology
License-File: LICENSE
Author-email: "Guilherme O. Santos" <guilherme.os1@aluno.ufop.edu.br>, Lucas Salgado Vieira <lucas.sv@aluno.ufop.edu.br>
Requires-Python: >=3.10
Project-URL: Documentation, https://oliveira-sh.github.io/pymocd/
Project-URL: Issues, https://github.com/oliveira-sh/pymocd/issues
Project-URL: Repository, https://github.com/oliveira-sh/pymocd
